dev_pinggy_am-0.0.7.dist-info/licenses/LICENSE
pinggy/__init__.py
pinggy/core.py
pinggy/loader.py
pinggy/pylib.py
pinggy/bin/pinggy.dll
pinggy/bin/pinggy.lib
dev_pinggy_am-0.0.7.dist-info/METADATA
dev_pinggy_am-0.0.7.dist-info/WHEEL
dev_pinggy_am-0.0.7.dist-info/top_level.txt
dev_pinggy_am-0.0.7.dist-info/RECORD
